gym_update2/__init__.py
gym_update2/envs/__init__.py
gym_update2/envs/update_env2.py
gym_update2-0.0.7.dist-info/LICENSE
gym_update2-0.0.7.dist-info/METADATA
gym_update2-0.0.7.dist-info/WHEEL
gym_update2-0.0.7.dist-info/top_level.txt
gym_update2-0.0.7.dist-info/RECORD
